xgpu-0.10.3.dist-info/top_level.txt
xgpu-0.10.3.dist-info/RECORD
xgpu-0.10.3.dist-info/LICENSE
xgpu-0.10.3.dist-info/METADATA
xgpu-0.10.3.dist-info/WHEEL
xgpu/textureformats.py
xgpu/renderdoc.py
xgpu/libwgpu_native.so
xgpu/_wgpu_native_cffi.cpython-39-x86_64-linux-gnu.so
xgpu/__init__.py
xgpu/_build_ext.py
xgpu/bindings.py
xgpu/extensions/helpers.py
xgpu/extensions/wrappers.py
xgpu/extensions/ktx.py
xgpu/extensions/standardimage.py
xgpu/extensions/texloader.py
xgpu/extensions/__init__.py
xgpu/extensions/vkformats.py
xgpu/extensions/glfw_window.py
xgpu/extensions/imgui_renderer.py
