Metadata-Version: 2.1
Name: xgpu
Version: 0.10.3
License: MIT License
Project-URL: Homepage, https://github.com/pyrym/xgpu
Requires-Python: >=3.7
License-File: LICENSE
Requires-Dist: cffi
Provides-Extra: gui
Requires-Dist: glfw ; extra == 'gui'
Requires-Dist: imgui ; extra == 'gui'
